pydvdid/__init__.py
pydvdid/crc64calculator.py
pydvdid/crc64result.py
pydvdid/exceptions.py
pydvdid/functions.py
pydvdid-1.1.data/scripts/pydvdid
pydvdid-1.1.dist-info/DESCRIPTION.rst
pydvdid-1.1.dist-info/METADATA
pydvdid-1.1.dist-info/RECORD
pydvdid-1.1.dist-info/WHEEL
pydvdid-1.1.dist-info/metadata.json
pydvdid-1.1.dist-info/top_level.txt
